Metadata-Version: 1.0
Name: udac-probability-bestnameever
Version: 0.1
Summary: Gaussian distributions
Home-page: UNKNOWN
Author: Sarah Rosenberg
Author-email: UNKNOWN
License: UNKNOWN
Platform: UNKNOWN
